totalvoice/__init__.py
totalvoice/cliente/__init__.py
totalvoice/cliente/api/__init__.py
totalvoice/cliente/api/audio.py
totalvoice/cliente/api/bina.py
totalvoice/cliente/api/chamada.py
totalvoice/cliente/api/composto.py
totalvoice/cliente/api/conferencia.py
totalvoice/cliente/api/conta.py
totalvoice/cliente/api/did.py
totalvoice/cliente/api/fila.py
totalvoice/cliente/api/minhaconta.py
totalvoice/cliente/api/sms.py
totalvoice/cliente/api/totalvoice.py
totalvoice/cliente/api/tts.py
totalvoice/cliente/api/central/__init__.py
totalvoice/cliente/api/central/ramal.py
totalvoice/cliente/api/central/ura.py
totalvoice/cliente/api/central/webphone.py
totalvoice/cliente/api/helper/__init__.py
totalvoice/cliente/api/helper/routes.py
totalvoice/cliente/api/helper/utils.py
totalvoice-1.7.0.dist-info/LICENSE
totalvoice-1.7.0.dist-info/METADATA
totalvoice-1.7.0.dist-info/WHEEL
totalvoice-1.7.0.dist-info/top_level.txt
totalvoice-1.7.0.dist-info/RECORD
