Metadata-Version: 2.1
Name: totalvoice
Version: 1.7.0
Summary: Biblioteca da Totalvoice em python
Home-page: https://github.com/totalvoice/totalvoice-python
Author: Carlos Henrique dos Santos
Author-email: carlos@totalvoice.com.br
License: MIT
Keywords: api rest totalvoice telefonia ligação
Platform: UNKNOWN
Classifier: Development Status :: 4 - Beta
Classifier: Intended Audience :: Developers
Classifier: Topic :: Education :: Testing
Classifier: License :: OSI Approved :: MIT License
Classifier: Programming Language :: Python :: 3
Classifier: Programming Language :: Python :: 3.2
Classifier: Programming Language :: Python :: 3.3
Classifier: Programming Language :: Python :: 3.4
